django_tippanee/__init__.py
django_tippanee/admin.py
django_tippanee/apps.py
django_tippanee/filters.py
django_tippanee/models.py
django_tippanee/pagination.py
django_tippanee/permissions.py
django_tippanee/serializers.py
django_tippanee/signals.py
django_tippanee/urls.py
django_tippanee/views.py
django_tippanee/migrations/0001_initial.py
django_tippanee/migrations/__init__.py
django_tippanee-0.1.0.dist-info/licenses/LICENSE
tests/__init__.py
tests/test_comments.py
django_tippanee-0.1.0.dist-info/METADATA
django_tippanee-0.1.0.dist-info/WHEEL
django_tippanee-0.1.0.dist-info/top_level.txt
django_tippanee-0.1.0.dist-info/RECORD
